README.txt
newcache.py
setup.py
django_newcache.egg-info/PKG-INFO
django_newcache.egg-info/SOURCES.txt
django_newcache.egg-info/dependency_links.txt
django_newcache.egg-info/not-zip-safe
django_newcache.egg-info/top_level.txt