Metadata-Version: 1.0
Name: django-newcache
Version: 0.2.2
Summary: Improved memcached cache backend for Django
Home-page: http://github.com/ericflo/django-newcache
Author: Eric Florenzano
Author-email: floguy@gmail.com
License: BSD
Platform: UNKNOWN
Classifier: Development Status :: 4 - Beta
Classifier: Intended Audience :: Developers
Classifier: Programming Language :: Python
Classifier: Topic :: Software Development :: Libraries :: Python Modules
Classifier: Framework :: Django
Classifier: Environment :: Web Environment
